setup.cfg
setup.py
kipavois/__init__.py
kipavois.egg-info/PKG-INFO
kipavois.egg-info/SOURCES.txt
kipavois.egg-info/dependency_links.txt
kipavois.egg-info/not-zip-safe
kipavois.egg-info/requires.txt
kipavois.egg-info/top_level.txt